wcbtfidf.py
Weighted_Class_Tfidf-1.0.3.dist-info/LICENSE
Weighted_Class_Tfidf-1.0.3.dist-info/METADATA
Weighted_Class_Tfidf-1.0.3.dist-info/WHEEL
Weighted_Class_Tfidf-1.0.3.dist-info/top_level.txt
Weighted_Class_Tfidf-1.0.3.dist-info/RECORD
