Metadata-Version: 2.1
Name: Weighted-Class-Tfidf
Version: 1.0.3
Summary: Custom implementation of tfidf for imbalanced datasets
Home-page: https://github.com/SauravPattnaikCS60/Weighted-Class-Tfidf
Author: Saurav Pattnaik
Classifier: Programming Language :: Python :: 3.6
Classifier: License :: OSI Approved :: MIT License
Classifier: Operating System :: OS Independent
Requires-Python: >=3.6
License-File: LICENSE
